openswitcher_proxy/__init__.py
openswitcher_proxy/__main__.py
openswitcher_proxy/cli-switch.py
openswitcher_proxy/error.py
openswitcher_proxy/frontend.py
openswitcher_proxy/frontend_httpapi.py
openswitcher_proxy/frontend_midi.py
openswitcher_proxy/frontend_mqtt.py
openswitcher_proxy/frontend_status.py
openswitcher_proxy/frontend_tcp.py
openswitcher_proxy/hardware.py
openswitcher_proxy-0.12.3.dist-info/LICENSE
openswitcher_proxy-0.12.3.dist-info/LICENSE-gpl3.txt
openswitcher_proxy-0.12.3.dist-info/LICENSE-lgpl3.txt
openswitcher_proxy-0.12.3.dist-info/METADATA
openswitcher_proxy-0.12.3.dist-info/WHEEL
openswitcher_proxy-0.12.3.dist-info/entry_points.txt
openswitcher_proxy-0.12.3.dist-info/top_level.txt
openswitcher_proxy-0.12.3.dist-info/RECORD
